windpowerlib/__init__.py
windpowerlib/data.py
windpowerlib/density.py
windpowerlib/modelchain.py
windpowerlib/power_curves.py
windpowerlib/power_output.py
windpowerlib/temperature.py
windpowerlib/tools.py
windpowerlib/turbine_cluster_modelchain.py
windpowerlib/wake_losses.py
windpowerlib/wind_farm.py
windpowerlib/wind_speed.py
windpowerlib/wind_turbine.py
windpowerlib/wind_turbine_cluster.py
windpowerlib/data/wind_efficiency_curves_dena.csv
windpowerlib/data/wind_efficiency_curves_knorr.csv
windpowerlib/data/default_turbine_data/power_coefficient_curves.csv
windpowerlib/data/default_turbine_data/power_curves.csv
windpowerlib/data/default_turbine_data/turbine_data.csv
windpowerlib/oedb/power_coefficient_curves.csv
windpowerlib/oedb/power_curves.csv
windpowerlib/oedb/turbine_data.csv
windpowerlib-0.2.2.dist-info/LICENSE
windpowerlib-0.2.2.dist-info/METADATA
windpowerlib-0.2.2.dist-info/WHEEL
windpowerlib-0.2.2.dist-info/top_level.txt
windpowerlib-0.2.2.dist-info/RECORD
