Metadata-Version: 2.1
Name: windpowerlib
Version: 0.2.2
Summary: Creating time series of wind power plants.
Home-page: http://github.com/wind-python/windpowerlib
Author: oemof developer group
Author-email: windpowerlib@rl-institut.de
License: MIT
License-File: LICENSE
Requires-Dist: pandas
Requires-Dist: requests
Provides-Extra: dev
Requires-Dist: jupyter; extra == "dev"
Requires-Dist: matplotlib; extra == "dev"
Requires-Dist: nbsphinx; extra == "dev"
Requires-Dist: numpy; extra == "dev"
Requires-Dist: pytest; extra == "dev"
Requires-Dist: pytest-notebook; extra == "dev"
Requires-Dist: sphinx>=1.4; extra == "dev"
Requires-Dist: sphinx_rtd_theme; extra == "dev"
